clirunner/__init__.py
clirunner/_compat.py
clirunner/_version.py
clirunner/_winconsole.py
clirunner/exceptions.py
clirunner/testing.py
clirunner/utils.py
clirunner-0.2.0.dist-info/licenses/LICENSE
clirunner-0.2.0.dist-info/licenses/LICENSE.Click
clirunner-0.2.0.dist-info/WHEEL
clirunner-0.2.0.dist-info/METADATA
clirunner-0.2.0.dist-info/RECORD
