Metadata-Version: 2.4
Name: clirunner
Version: 0.2.0
Summary: CliRunner test runner for command line applications.
Author-email: Rhet Turnbull <rturnbull+git@gmail.com>
Classifier: License :: OSI Approved :: BSD License
Classifier: Topic :: Software Development :: Testing
License-File: LICENSE
License-File: LICENSE.Click
Requires-Dist: flit>=3.9.0 ; extra == "dev"
Requires-Dist: cogapp>=3.3.0 ; extra == "dev"
Requires-Dist: bump2version>=1.0.1 ; extra == "dev"
Requires-Dist: doit>=0.36.0 ; extra == "dev"
Requires-Dist: mkdocs>=1.4.2 ; extra == "docs"
Requires-Dist: mkdocs-material>=9.0.13 ; extra == "docs"
Requires-Dist: mkdocstrings-python>=0.8.3 ; extra == "docs"
Requires-Dist: pytest>=7.4.2 ; extra == "test"
Requires-Dist: pytest-cov ; extra == "test"
Requires-Dist: mypy>=1.6.1 ; extra == "test"
Requires-Dist: instld>=0.0.23 ; extra == "test"
Project-URL: Home, https://github.com/RhetTbull/clirunner
Project-URL: Issues, https://github.com/RhetTbull/clirunner/issues
Project-URL: Source, https://github.com/RhetTbull/clirunner
Provides-Extra: dev
Provides-Extra: docs
Provides-Extra: test
